akaneko/__init__.py
akaneko/ext.py
akaneko/nsfw.py
akaneko/req.py
akaneko/sfw.py
akanekopy-1.1.4.dist-info/METADATA
akanekopy-1.1.4.dist-info/WHEEL
akanekopy-1.1.4.dist-info/top_level.txt
akanekopy-1.1.4.dist-info/RECORD
