Metadata-Version: 2.1
Name: akanekopy
Version: 1.1.4
Summary: Akaneko for Python 3 and above
Home-page: https://github.com/RaphielHS/akaneko-wrapper
Author: RaphielHS
Author-email: mightybfggt@gmail.com
License: MIT license
Keywords: akaneko anime wallpaper hentai
Platform: UNKNOWN
Classifier: License :: OSI Approved :: MIT License
Classifier: Operating System :: OS Independent
Classifier: Development Status :: 4 - Beta
Classifier: Natural Language :: English
Classifier: Operating System :: Microsoft :: Windows :: Windows 10
Classifier: Programming Language :: Python :: 3
Classifier: Programming Language :: Python :: 3.9
Classifier: Topic :: Internet
Requires-Python: >=3.0
Requires-Dist: requests
